eces_eg_weather_package/__init__.py
eces_eg_weather_package/main.py
eces_eg_weather_package-1.1.0.dist-info/METADATA
eces_eg_weather_package-1.1.0.dist-info/WHEEL
eces_eg_weather_package-1.1.0.dist-info/top_level.txt
eces_eg_weather_package-1.1.0.dist-info/RECORD
